fastgenomics_cli/__init__.py
fastgenomics_cli/fg_cli.py
fastgenomics_cli/fg_configurationupdater.py
fastgenomics_cli/fg_upload.py
fastgenomics_cli-0.13.0.dist-info/entry_points.txt
fastgenomics_cli-0.13.0.dist-info/WHEEL
fastgenomics_cli-0.13.0.dist-info/METADATA
fastgenomics_cli-0.13.0.dist-info/RECORD
