Metadata-Version: 2.1
Name: fastgenomics-cli
Version: 0.13.0
Summary: FASTGenomics CLI
Home-page: https://beta.fastgenomics.org
Author: FASTGenomics
Author-email: team@fastgenomics.org
Requires-Dist: fastgenomics >= 3.4
Requires-Dist: requests >=2
Requires-Dist: tqdm >=4
Requires-Dist: update_checker >= 0.18
